golpo/__init__.py
golpo/client.py
golpo/client.pyi
golpo-0.9.8.dist-info/METADATA
golpo-0.9.8.dist-info/WHEEL
golpo-0.9.8.dist-info/RECORD
