Metadata-Version: 2.4
Name: golpo
Version: 0.9.8
Summary: Python SDK for Golpo AI-generated explainer videos and podcasts.
Project-URL: Homepage, https://video.golpoai.com
Author-email: Golpo <shreyas2@stanford.edu>
License: MIT
Requires-Python: >=3.8
Requires-Dist: requests>=2.31
